encryptor/__init__.py
encryptor/__main__.py
encryptor/my_module.py
encryptor/bin/__init__.py
encryptor/bin/entry.py
data_encryptor-0.0.1.dist-info/LICENSE
data_encryptor-0.0.1.dist-info/METADATA
data_encryptor-0.0.1.dist-info/WHEEL
data_encryptor-0.0.1.dist-info/entry_points.txt
data_encryptor-0.0.1.dist-info/top_level.txt
data_encryptor-0.0.1.dist-info/RECORD
